ThresholdPicker/Test_all.py
ThresholdPicker/ThresholdPicker.py
ThresholdPicker/__init__.py
ThresholdPicker/test.py
ThresholdPicker/utils.py
ThresholdPicker-0.0.5.dist-info/LICENSE.txt
ThresholdPicker-0.0.5.dist-info/METADATA
ThresholdPicker-0.0.5.dist-info/WHEEL
ThresholdPicker-0.0.5.dist-info/top_level.txt
ThresholdPicker-0.0.5.dist-info/RECORD
