Metadata-Version: 2.1
Name: ThresholdPicker
Version: 0.0.5
Summary: Thereshold Picker for Binary Classifiers
Home-page: https://github.com/Gsend/ThersholdPicker.git
Author: Gilad Senderovich
Author-email: giladsnd@gmail.com
License: UNKNOWN
Project-URL: Bug Tracker, https://github.com/Gsend/ThersholdPicker/issues
Platform: UNKNOWN
Classifier: Programming Language :: Python :: 3
Classifier: License :: OSI Approved :: MIT License
Classifier: Operating System :: OS Independent
Requires-Python: >=3.6
License-File: LICENSE.txt
